keycloak_httpd_client/__init__.py
keycloak_httpd_client/keycloak_rest.py
keycloak_httpd_client/utils.py
keycloak_httpd_client_install-1.2.2.data/scripts/keycloak-httpd-client-install
keycloak_httpd_client_install-1.2.2.data/scripts/keycloak-rest
usr/share/keycloak-httpd-client-install/templates/mellon_httpd.conf
usr/share/keycloak-httpd-client-install/templates/oidc-client-registration.tpl
usr/share/keycloak-httpd-client-install/templates/oidc-client-representation.tpl
usr/share/keycloak-httpd-client-install/templates/oidc_httpd.conf
usr/share/keycloak-httpd-client-install/templates/sp_metadata.tpl
keycloak_httpd_client_install-1.2.2.dist-info/LICENSE.txt
keycloak_httpd_client_install-1.2.2.dist-info/METADATA
keycloak_httpd_client_install-1.2.2.dist-info/WHEEL
keycloak_httpd_client_install-1.2.2.dist-info/top_level.txt
keycloak_httpd_client_install-1.2.2.dist-info/RECORD
