Metadata-Version: 2.1
Name: keycloak-httpd-client-install
Version: 1.2.2
Summary: Tools to configure Apache HTTPD as Keycloak client
Home-page: https://github.com/latchset/keycloak-httpd-client-install
Author: John Dennis
Author-email: jdennis@redhat.com
License: GPLv3
Platform: UNKNOWN
Classifier: Programming Language :: Python
Classifier: Programming Language :: Python :: 3
Classifier: Development Status :: 5 - Production/Stable
Classifier: License :: OSI Approved :: GNU General Public License v3 or later (GPLv3+)
Classifier: Operating System :: POSIX
Requires-Dist: requests
Requires-Dist: requests-oauthlib
Requires-Dist: jinja2
Requires-Dist: six
Requires-Dist: setuptools
Requires-Dist: lxml
